twophase/__init__.py
twophase/client_gui.py
twophase/client_gui2.py
twophase/computer_vision.py
twophase/coord.py
twophase/cubie.py
twophase/defs.py
twophase/enums.py
twophase/face.py
twophase/misc.py
twophase/moves.py
twophase/performance.py
twophase/pruning.py
twophase/server.py
twophase/sockets.py
twophase/solver.py
twophase/start_server.py
twophase/symmetries.py
twophase/vision2.py
twophase/vision_params.py
RubikTwoPhase-1.0.9.dist-info/LICENSE
RubikTwoPhase-1.0.9.dist-info/METADATA
RubikTwoPhase-1.0.9.dist-info/WHEEL
RubikTwoPhase-1.0.9.dist-info/top_level.txt
RubikTwoPhase-1.0.9.dist-info/RECORD
