Metadata-Version: 2.1
Name: RubikTwoPhase
Version: 1.0.9
Summary: A package to solve Rubik's cube in less than 19 moves on average with the two-phase algorithm.
Home-page: https://github.com/hkociemba/RubiksCube-TwophaseSolver
Author: Herbert Kociemba
Author-email: kociemba@t-online.de
License: UNKNOWN
Project-URL: Bug Tracker, https://github.com/hkociemba/RubiksCube-TwophaseSolver/issues
Keywords: 'Rubik's Cube,Rubik,cube,solver,twophase,two-phase,algorithm,Kociemba'
Platform: UNKNOWN
Classifier: Programming Language :: Python :: 3
Classifier: License :: OSI Approved :: GNU General Public License v3 or later (GPLv3+)
Classifier: Operating System :: OS Independent
Requires-Python: >=3.4
License-File: LICENSE
